[{"id": "ChIJQ-yptR5E1moRJNqlNwsK7SM", "types": ["dentist", "dental_clinic", "medical_clinic", "service", "health", "point_of_interest", "establishment"], "formattedAddress": "61 Upper Heidelberg Rd, Ivanhoe VIC 3079, Australia", "addressComponents": [{"longText": "61", "shortText": "61", "types": ["street_number"], "languageCode": "en-AU"}, {"longText": "Upper Heidelberg Road", "shortText": "Upper Heidelberg Rd", "types": ["route"], "languageCode": "en"}, {"longText": "Ivanhoe", "shortText": "Ivanhoe", "types": ["locality", "political"], "languageCode": "en"}, {"longText": "Banyule City", "shortText": "Banyule", "types": ["administrative_area_level_2", "political"], "languageCode": "en"}, {"longText": "Victoria", "shortText": "VIC", "types": ["administrative_area_level_1", "political"], "languageCode": "en"}, {"longText": "Australia", "shortText": "AU", "types": ["country", "political"], "languageCode": "en"}, {"longText": "3079", "shortText": "3079", "types": ["postal_code"], "languageCode": "en-AU"}], "location": {"latitude": -37.7705815, "longitude": 145.0407333}, "businessStatus": "OPERATIONAL", "displayName": {"text": "Dentists of Ivanhoe", "languageCode": "en"}, "primaryTypeDisplayName": {"text": "Dentist", "languageCode": "en-AU"}, "primaryType": "dentist", "shortFormattedAddress": "61 Upper Heidelberg Rd, Ivanhoe"}, {"id": "ChIJ_cPynY9F1moRFCFcuhNRi44", "types": ["dental_clinic", "dentist", "medical_clinic", "health", "point_of_interest", "establishment"], "formattedAddress": "Shop 2/1045 Heidelberg Rd, Ivanhoe VIC 3079, Australia", "addressComponents": [{"longText": "Shop 2", "shortText": "Shop 2", "types": ["subpremise"], "languageCode": "en"}, {"longText": "1045", "shortText": "1045", "types": ["street_number"], "languageCode": "en-AU"}, {"longText": "Heidelberg Road", "shortText": "Heidelberg Rd", "types": ["route"], "languageCode": "en"}, {"longText": "Ivanhoe", "shortText": "Ivanhoe", "types": ["locality", "political"], "languageCode": "en"}, {"longText": "Banyule City", "shortText": "Banyule", "types": ["administrative_area_level_2", "political"], "languageCode": "en"}, {"longText": "Victoria", "shortText": "VIC", "types": ["administrative_area_level_1", "political"], "languageCode": "en"}, {"longText": "Australia", "shortText": "AU", "types": ["country", "political"], "languageCode": "en"}, {"longText": "3079", "shortText": "3079", "types": ["postal_code"], "languageCode": "en-AU"}], "location": {"latitude": -37.774788099999995, "longitude": 145.0391789}, "businessStatus": "OPERATIONAL", "displayName": {"text": "Prodental Melbourne", "languageCode": "en"}, "primaryTypeDisplayName": {"text": "Dental Clinic", "languageCode": "en-AU"}, "primaryType": "dental_clinic", "shortFormattedAddress": "Shop 2/1045 Heidelberg Rd, Ivanhoe"}, {"id": "ChIJzawVyB1E1moRNaFrI9Ox8Jg", "types": ["dentist", "health", "point_of_interest", "establishment"], "formattedAddress": "Unit 2/63 Upper Heidelberg Rd, Ivanhoe VIC 3079, Australia", "addressComponents": [{"longText": "Unit 2", "shortText": "Unit 2", "types": ["subpremise"], "languageCode": "en"}, {"longText": "63", "shortText": "63", "types": ["street_number"], "languageCode": "en-AU"}, {"longText": "Upper Heidelberg Road", "shortText": "Upper Heidelberg Rd", "types": ["route"], "languageCode": "en"}, {"longText": "Ivanhoe", "shortText": "Ivanhoe", "types": ["locality", "political"], "languageCode": "en"}, {"longText": "Banyule City", "shortText": "Banyule", "types": ["administrative_area_level_2", "political"], "languageCode": "en"}, {"longText": "Victoria", "shortText": "VIC", "types": ["administrative_area_level_1", "political"], "languageCode": "en"}, {"longText": "Australia", "shortText": "AU", "types": ["country", "political"], "languageCode": "en"}, {"longText": "3079", "shortText": "3079", "types": ["postal_code"], "languageCode": "en-AU"}], "location": {"latitude": -37.7703346, "longitude": 145.0408196}, "businessStatus": "OPERATIONAL", "displayName": {"text": "Charisma Dental", "languageCode": "en"}, "primaryTypeDisplayName": {"text": "Dentist", "languageCode": "en-AU"}, "primaryType": "dentist", "shortFormattedAddress": "Unit 2/63 Upper Heidelberg Rd, Ivanhoe"}, {"id": "ChIJ9VHStB5E1moR2B1gEd14DL8", "types": ["dentist", "dental_clinic", "medical_clinic", "service", "health", "point_of_interest", "establishment"], "formattedAddress": "61 Upper Heidelberg Rd, Ivanhoe VIC 3079, Australia", "addressComponents": [{"longText": "61", "shortText": "61", "types": ["street_number"], "languageCode": "en-AU"}, {"longText": "Upper Heidelberg Road", "shortText": "Upper Heidelberg Rd", "types": ["route"], "languageCode": "en"}, {"longText": "Ivanhoe", "shortText": "Ivanhoe", "types": ["locality", "political"], "languageCode": "en"}, {"longText": "Banyule City", "shortText": "Banyule", "types": ["administrative_area_level_2", "political"], "languageCode": "en"}, {"longText": "Victoria", "shortText": "VIC", "types": ["administrative_area_level_1", "political"], "languageCode": "en"}, {"longText": "Australia", "shortText": "AU", "types": ["country", "political"], "languageCode": "en"}, {"longText": "3079", "shortText": "3079", "types": ["postal_code"], "languageCode": "en-AU"}], "location": {"latitude": -37.7705815, "longitude": 145.0407333}, "businessStatus": "OPERATIONAL", "displayName": {"text": "Dr. Shehan Warusevitane", "languageCode": "en"}, "primaryTypeDisplayName": {"text": "Dentist", "languageCode": "en-AU"}, "primaryType": "dentist", "shortFormattedAddress": "61 Upper Heidelberg Rd, Ivanhoe"}, {"id": "ChIJQ-yptR5E1moRUg2yW4APdqo", "types": ["dentist", "health", "point_of_interest", "establishment"], "formattedAddress": "61 Upper Heidelberg Rd, Ivanhoe VIC 3079, Australia", "addressComponents": [{"longText": "61", "shortText": "61", "types": ["street_number"], "languageCode": "en-AU"}, {"longText": "Upper Heidelberg Road", "shortText": "Upper Heidelberg Rd", "types": ["route"], "languageCode": "en"}, {"longText": "Ivanhoe", "shortText": "Ivanhoe", "types": ["locality", "political"], "languageCode": "en"}, {"longText": "Banyule City", "shortText": "Banyule", "types": ["administrative_area_level_2", "political"], "languageCode": "en"}, {"longText": "Victoria", "shortText": "VIC", "types": ["administrative_area_level_1", "political"], "languageCode": "en"}, {"longText": "Australia", "shortText": "AU", "types": ["country", "political"], "languageCode": "en"}, {"longText": "3079", "shortText": "3079", "types": ["postal_code"], "languageCode": "en-AU"}], "location": {"latitude": -37.7705815, "longitude": 145.0407333}, "businessStatus": "CLOSED_TEMPORARILY", "displayName": {"text": "Dr. Susan Portbury", "languageCode": "en"}, "primaryTypeDisplayName": {"text": "Dentist", "languageCode": "en-AU"}, "primaryType": "dentist", "shortFormattedAddress": "61 Upper Heidelberg Rd, Ivanhoe"}]