[{"id": "ChIJ-3X4J6RD1moR5yOs7IFatvo", "types": ["physiotherapist", "massage_spa", "spa", "medical_clinic", "massage", "service", "health", "point_of_interest", "establishment"], "formattedAddress": "769A Glenferrie Rd, Hawthorn VIC 3122, Australia", "addressComponents": [{"longText": "769A", "shortText": "769A", "types": ["street_number"], "languageCode": "en-AU"}, {"longText": "Glenferrie Road", "shortText": "Glenferrie Rd", "types": ["route"], "languageCode": "en"}, {"longText": "Hawthorn", "shortText": "Hawthorn", "types": ["locality", "political"], "languageCode": "en"}, {"longText": "Boroondara City", "shortText": "Boroondara", "types": ["administrative_area_level_2", "political"], "languageCode": "en"}, {"longText": "Victoria", "shortText": "VIC", "types": ["administrative_area_level_1", "political"], "languageCode": "en"}, {"longText": "Australia", "shortText": "AU", "types": ["country", "political"], "languageCode": "en"}, {"longText": "3122", "shortText": "3122", "types": ["postal_code"], "languageCode": "en-AU"}], "location": {"latitude": -37.8173469, "longitude": 145.0361671}, "businessStatus": "OPERATIONAL", "displayName": {"text": "Cheewa Aroma Remedial Thai Massage", "languageCode": "en"}, "primaryTypeDisplayName": {"text": "Physiotherapist", "languageCode": "en-AU"}, "primaryType": "physiotherapist", "shortFormattedAddress": "769A Glenferrie Rd, Hawthorn"}, {"id": "ChIJ_-c-rzNC1moRtrKOVJDsomA", "types": ["physiotherapist", "health", "point_of_interest", "establishment"], "formattedAddress": "1 Grace St, Hawthorn VIC 3122, Australia", "addressComponents": [{"longText": "1", "shortText": "1", "types": ["street_number"], "languageCode": "en-AU"}, {"longText": "Grace Street", "shortText": "Grace St", "types": ["route"], "languageCode": "en"}, {"longText": "Hawthorn", "shortText": "Hawthorn", "types": ["locality", "political"], "languageCode": "en"}, {"longText": "Boroondara City", "shortText": "Boroondara", "types": ["administrative_area_level_2", "political"], "languageCode": "en"}, {"longText": "Victoria", "shortText": "VIC", "types": ["administrative_area_level_1", "political"], "languageCode": "en"}, {"longText": "Australia", "shortText": "AU", "types": ["country", "political"], "languageCode": "en"}, {"longText": "3122", "shortText": "3122", "types": ["postal_code"], "languageCode": "en-AU"}], "location": {"latitude": -37.8209622, "longitude": 145.034546}, "businessStatus": "OPERATIONAL", "displayName": {"text": "Performance Plus Healthcare Hawthorn", "languageCode": "en"}, "primaryTypeDisplayName": {"text": "Physiotherapist", "languageCode": "en-AU"}, "primaryType": "physiotherapist", "shortFormattedAddress": "1 Grace St, Hawthorn"}, {"id": "ChIJZVfBYTRC1moRcTs4PiEmABU", "types": ["physiotherapist", "medical_clinic", "health", "point_of_interest", "establishment"], "formattedAddress": "1 Grace St, Hawthorn VIC 3122, Australia", "addressComponents": [{"longText": "1", "shortText": "1", "types": ["street_number"], "languageCode": "en-AU"}, {"longText": "Grace Street", "shortText": "Grace St", "types": ["route"], "languageCode": "en"}, {"longText": "Hawthorn", "shortText": "Hawthorn", "types": ["locality", "political"], "languageCode": "en"}, {"longText": "Boroondara City", "shortText": "Boroondara", "types": ["administrative_area_level_2", "political"], "languageCode": "en"}, {"longText": "Victoria", "shortText": "VIC", "types": ["administrative_area_level_1", "political"], "languageCode": "en"}, {"longText": "Australia", "shortText": "AU", "types": ["country", "political"], "languageCode": "en"}, {"longText": "3122", "shortText": "3122", "types": ["postal_code"], "languageCode": "en-AU"}], "location": {"latitude": -37.820941399999995, "longitude": 145.0344381}, "businessStatus": "OPERATIONAL", "displayName": {"text": "Glenferrie Physiotherapy Centre", "languageCode": "en"}, "primaryTypeDisplayName": {"text": "Medical Clinic", "languageCode": "en-AU"}, "primaryType": "medical_clinic", "shortFormattedAddress": "1 Grace St, Hawthorn"}]