[{"id": "ChIJwXXc7DFE1moRZpeY1dEjBMw", "types": ["doctor", "medical_clinic", "health", "point_of_interest", "establishment"], "formattedAddress": "Level 1/365 Bell St, Bellfield VIC 3081, Australia", "addressComponents": [{"longText": "Level 1", "shortText": "Level 1", "types": ["subpremise"], "languageCode": "en"}, {"longText": "365", "shortText": "365", "types": ["street_number"], "languageCode": "en-AU"}, {"longText": "Bell Street", "shortText": "Bell St", "types": ["route"], "languageCode": "en"}, {"longText": "Bellfield", "shortText": "Bellfield", "types": ["locality", "political"], "languageCode": "en"}, {"longText": "Banyule City", "shortText": "Banyule", "types": ["administrative_area_level_2", "political"], "languageCode": "en"}, {"longText": "Victoria", "shortText": "VIC", "types": ["administrative_area_level_1", "political"], "languageCode": "en"}, {"longText": "Australia", "shortText": "AU", "types": ["country", "political"], "languageCode": "en"}, {"longText": "3081", "shortText": "3081", "types": ["postal_code"], "languageCode": "en-AU"}], "location": {"latitude": -37.7495785, "longitude": 145.037}, "businessStatus": "OPERATIONAL", "displayName": {"text": "Melbourne Comprehensive Eye Surgeons - Cataract Surgery", "languageCode": "en"}, "primaryTypeDisplayName": {"text": "Doctor", "languageCode": "en-AU"}, "primaryType": "doctor", "shortFormattedAddress": "Level 1/365 Bell St, Bellfield"}, {"id": "ChIJAzvA3y1E1moRXt_BH_4Zrto", "types": ["doctor", "medical_clinic", "health", "service", "point_of_interest", "establishment"], "formattedAddress": "337 Bell St, Bellfield VIC 3081, Australia", "addressComponents": [{"longText": "337", "shortText": "337", "types": ["street_number"], "languageCode": "en-AU"}, {"longText": "Bell Street", "shortText": "Bell St", "types": ["route"], "languageCode": "en"}, {"longText": "Bellfield", "shortText": "Bellfield", "types": ["locality", "political"], "languageCode": "en"}, {"longText": "Banyule City", "shortText": "Banyule", "types": ["administrative_area_level_2", "political"], "languageCode": "en"}, {"longText": "Victoria", "shortText": "VIC", "types": ["administrative_area_level_1", "political"], "languageCode": "en"}, {"longText": "Australia", "shortText": "AU", "types": ["country", "political"], "languageCode": "en"}, {"longText": "3081", "shortText": "3081", "types": ["postal_code"], "languageCode": "en-AU"}], "location": {"latitude": -37.7498772, "longitude": 145.0397401}, "businessStatus": "OPERATIONAL", "displayName": {"text": "Dorevitch Pathology Bellfield", "languageCode": "en"}, "primaryTypeDisplayName": {"text": "Doctor", "languageCode": "en-AU"}, "primaryType": "doctor", "shortFormattedAddress": "337 Bell St, Bellfield"}, {"id": "ChIJDVnOdC5E1moRriDP0U-tSxg", "types": ["doctor", "health", "point_of_interest", "establishment"], "formattedAddress": "337 Bell St, Bellfield VIC 3081, Australia", "addressComponents": [{"longText": "337", "shortText": "337", "types": ["street_number"], "languageCode": "en-AU"}, {"longText": "Bell Street", "shortText": "Bell St", "types": ["route"], "languageCode": "en"}, {"longText": "Bellfield", "shortText": "Bellfield", "types": ["locality", "political"], "languageCode": "en"}, {"longText": "Banyule City", "shortText": "Banyule", "types": ["administrative_area_level_2", "political"], "languageCode": "en"}, {"longText": "Victoria", "shortText": "VIC", "types": ["administrative_area_level_1", "political"], "languageCode": "en"}, {"longText": "Australia", "shortText": "AU", "types": ["country", "political"], "languageCode": "en"}, {"longText": "3081", "shortText": "3081", "types": ["postal_code"], "languageCode": "en-AU"}], "location": {"latitude": -37.749933999999996, "longitude": 145.03972}, "businessStatus": "OPERATIONAL", "displayName": {"text": "Bellfield Medical Centre-Mukri D", "languageCode": "en"}, "primaryTypeDisplayName": {"text": "Doctor", "languageCode": "en-AU"}, "primaryType": "doctor", "shortFormattedAddress": "337 Bell St, Bellfield"}, {"id": "ChIJ01QuThRE1moRFT2m0rlatxQ", "types": ["doctor", "health", "point_of_interest", "establishment"], "formattedAddress": "134/144 Ford St, Ivanhoe VIC 3079, Australia", "addressComponents": [{"longText": "134", "shortText": "134", "types": ["subpremise"], "languageCode": "en"}, {"longText": "144", "shortText": "144", "types": ["street_number"], "languageCode": "en-AU"}, {"longText": "Ford Street", "shortText": "Ford St", "types": ["route"], "languageCode": "en"}, {"longText": "Ivanhoe", "shortText": "Ivanhoe", "types": ["locality", "political"], "languageCode": "en"}, {"longText": "Banyule City", "shortText": "Banyule", "types": ["administrative_area_level_2", "political"], "languageCode": "en"}, {"longText": "Victoria", "shortText": "VIC", "types": ["administrative_area_level_1", "political"], "languageCode": "en"}, {"longText": "Australia", "shortText": "AU", "types": ["country", "political"], "languageCode": "en"}, {"longText": "3079", "shortText": "3079", "types": ["postal_code"], "languageCode": "en-AU"}], "location": {"latitude": -37.7634462, "longitude": 145.0307755}, "businessStatus": "OPERATIONAL", "displayName": {"text": "Lim Terence CDR", "languageCode": "en"}, "primaryTypeDisplayName": {"text": "Doctor", "languageCode": "en-AU"}, "primaryType": "doctor", "shortFormattedAddress": "134/144 Ford St, Ivanhoe"}, {"id": "ChIJed-CLCVE1moRqGZFW5zkl3M", "types": ["doctor", "health", "point_of_interest", "establishment"], "formattedAddress": "15 Daphne Cres, Bellfield VIC 3081, Australia", "addressComponents": [{"longText": "15", "shortText": "15", "types": ["street_number"], "languageCode": "en-AU"}, {"longText": "Daphne Crescent", "shortText": "Daphne Cres", "types": ["route"], "languageCode": "en"}, {"longText": "Bellfield", "shortText": "Bellfield", "types": ["locality", "political"], "languageCode": "en"}, {"longText": "Banyule City", "shortText": "Banyule", "types": ["administrative_area_level_2", "political"], "languageCode": "en"}, {"longText": "Victoria", "shortText": "VIC", "types": ["administrative_area_level_1", "political"], "languageCode": "en"}, {"longText": "Australia", "shortText": "AU", "types": ["country", "political"], "languageCode": "en"}, {"longText": "3081", "shortText": "3081", "types": ["postal_code"], "languageCode": "en-AU"}], "location": {"latitude": -37.7553949, "longitude": 145.0404244}, "businessStatus": "OPERATIONAL", "displayName": {"text": "Maternal & Child Health by Banyule City Council", "languageCode": "en"}, "primaryTypeDisplayName": {"text": "Doctor", "languageCode": "en-AU"}, "primaryType": "doctor", "shortFormattedAddress": "15 Daphne Cres, Bellfield"}, {"id": "ChIJLz2AFU9E1moRE4f6NYFe69s", "types": ["doctor", "health", "point_of_interest", "establishment"], "formattedAddress": "140 Bell St, Preston VIC 3072, Australia", "addressComponents": [{"longText": "140", "shortText": "140", "types": ["street_number"], "languageCode": "en-AU"}, {"longText": "Bell Street", "shortText": "Bell St", "types": ["route"], "languageCode": "en"}, {"longText": "Preston", "shortText": "Preston", "types": ["locality", "political"], "languageCode": "en"}, {"longText": "Darebin City", "shortText": "Darebin", "types": ["administrative_area_level_2", "political"], "languageCode": "en"}, {"longText": "Victoria", "shortText": "VIC", "types": ["administrative_area_level_1", "political"], "languageCode": "en"}, {"longText": "Australia", "shortText": "AU", "types": ["country", "political"], "languageCode": "en"}, {"longText": "3072", "shortText": "3072", "types": ["postal_code"], "languageCode": "en-AU"}], "location": {"latitude": -37.7465603, "longitude": 145.02039589999998}, "businessStatus": "OPERATIONAL", "displayName": {"text": "Seedling Osteopathy Body Wellness Clinic", "languageCode": "en"}, "primaryTypeDisplayName": {"text": "Doctor", "languageCode": "en-AU"}, "primaryType": "doctor", "shortFormattedAddress": "140 Bell St, Preston"}, {"id": "ChIJDVnOdC5E1moRiGb__5_HTLs", "types": ["doctor", "health", "point_of_interest", "establishment"], "formattedAddress": "337 Bell St, Bellfield VIC 3081, Australia", "addressComponents": [{"longText": "337", "shortText": "337", "types": ["street_number"], "languageCode": "en-AU"}, {"longText": "Bell Street", "shortText": "Bell St", "types": ["route"], "languageCode": "en"}, {"longText": "Bellfield", "shortText": "Bellfield", "types": ["locality", "political"], "languageCode": "en"}, {"longText": "Banyule City", "shortText": "Banyule", "types": ["administrative_area_level_2", "political"], "languageCode": "en"}, {"longText": "Victoria", "shortText": "VIC", "types": ["administrative_area_level_1", "political"], "languageCode": "en"}, {"longText": "Australia", "shortText": "AU", "types": ["country", "political"], "languageCode": "en"}, {"longText": "3081", "shortText": "3081", "types": ["postal_code"], "languageCode": "en-AU"}], "location": {"latitude": -37.749933999999996, "longitude": 145.03972}, "businessStatus": "OPERATIONAL", "displayName": {"text": "Bellfield Medical Centre-Daniel Valsa", "languageCode": "en"}, "primaryTypeDisplayName": {"text": "Doctor", "languageCode": "en-AU"}, "primaryType": "doctor", "shortFormattedAddress": "337 Bell St, Bellfield"}]