[{"id": "ChIJNYZcP3xD1moRMNpfQzrSAS0", "types": ["skin_care_clinic", "medical_center", "medical_clinic", "hospital", "doctor", "service", "health", "point_of_interest", "establishment"], "formattedAddress": "295 High St, Northcote VIC 3070, Australia", "addressComponents": [{"longText": "295", "shortText": "295", "types": ["street_number"], "languageCode": "en-AU"}, {"longText": "High Street", "shortText": "High St", "types": ["route"], "languageCode": "en"}, {"longText": "Northcote", "shortText": "Northcote", "types": ["locality", "political"], "languageCode": "en"}, {"longText": "Darebin City", "shortText": "Darebin", "types": ["administrative_area_level_2", "political"], "languageCode": "en"}, {"longText": "Victoria", "shortText": "VIC", "types": ["administrative_area_level_1", "political"], "languageCode": "en"}, {"longText": "Australia", "shortText": "AU", "types": ["country", "political"], "languageCode": "en"}, {"longText": "3070", "shortText": "3070", "types": ["postal_code"], "languageCode": "en-AU"}], "location": {"latitude": -37.771772, "longitude": 144.998098}, "businessStatus": "OPERATIONAL", "displayName": {"text": "Doctors of Northcote", "languageCode": "en"}, "primaryTypeDisplayName": {"text": "Doctor", "languageCode": "en-AU"}, "primaryType": "doctor", "shortFormattedAddress": "295 High St, Northcote"}, {"id": "ChIJtfOoQXxD1moRf7TmRDAK30k", "types": ["medical_lab", "medical_clinic", "doctor", "health", "point_of_interest", "establishment"], "formattedAddress": "295 High St, Northcote VIC 3070, Australia", "addressComponents": [{"longText": "295", "shortText": "295", "types": ["street_number"], "languageCode": "en-AU"}, {"longText": "High Street", "shortText": "High St", "types": ["route"], "languageCode": "en"}, {"longText": "Northcote", "shortText": "Northcote", "types": ["locality", "political"], "languageCode": "en"}, {"longText": "Darebin City", "shortText": "Darebin", "types": ["administrative_area_level_2", "political"], "languageCode": "en"}, {"longText": "Victoria", "shortText": "VIC", "types": ["administrative_area_level_1", "political"], "languageCode": "en"}, {"longText": "Australia", "shortText": "AU", "types": ["country", "political"], "languageCode": "en"}, {"longText": "3070", "shortText": "3070", "types": ["postal_code"], "languageCode": "en-AU"}], "location": {"latitude": -37.7717714, "longitude": 144.9981534}, "businessStatus": "OPERATIONAL", "displayName": {"text": "Australian Clinical Labs Northcote", "languageCode": "en"}, "primaryTypeDisplayName": {"text": "Doctor", "languageCode": "en-AU"}, "primaryType": "doctor", "shortFormattedAddress": "295 High St, Northcote"}, {"id": "ChIJ05nNLftD1moRxnfzB7XhiqU", "types": ["medical_clinic", "doctor", "service", "health", "point_of_interest", "establishment"], "formattedAddress": "Corner Level 1 282 High Street &, Mitchell St, Northcote VIC 3070, Australia", "addressComponents": [{"longText": "Corner Level 1 282 High Street &", "languageCode": "en"}, {"longText": "Mitchell Street", "shortText": "Mitchell St", "types": ["route"], "languageCode": "en"}, {"longText": "Northcote", "shortText": "Northcote", "types": ["locality", "political"], "languageCode": "en"}, {"longText": "Darebin City", "shortText": "Darebin", "types": ["administrative_area_level_2", "political"], "languageCode": "en"}, {"longText": "Victoria", "shortText": "VIC", "types": ["administrative_area_level_1", "political"], "languageCode": "en"}, {"longText": "Australia", "shortText": "AU", "types": ["country", "political"], "languageCode": "en"}, {"longText": "3070", "shortText": "3070", "types": ["postal_code"], "languageCode": "en-AU"}], "location": {"latitude": -37.771893, "longitude": 144.99864900000003}, "businessStatus": "OPERATIONAL", "displayName": {"text": "Dorevitch Pathology Northcote Corner High Street & Mitchell Street", "languageCode": "en"}, "primaryTypeDisplayName": {"text": "Doctor", "languageCode": "en-AU"}, "primaryType": "doctor", "shortFormattedAddress": "Corner Level 1 282 High Street &, Mitchell St, Northcote"}, {"id": "ChIJX4OdQHxD1moR_vBkqw09vos", "types": ["doctor", "health", "point_of_interest", "establishment"], "formattedAddress": "295 High St, Northcote VIC 3070, Australia", "addressComponents": [{"longText": "295", "shortText": "295", "types": ["street_number"], "languageCode": "en-AU"}, {"longText": "High Street", "shortText": "High St", "types": ["route"], "languageCode": "en"}, {"longText": "Northcote", "shortText": "Northcote", "types": ["locality", "political"], "languageCode": "en"}, {"longText": "Darebin City", "shortText": "Darebin", "types": ["administrative_area_level_2", "political"], "languageCode": "en"}, {"longText": "Victoria", "shortText": "VIC", "types": ["administrative_area_level_1", "political"], "languageCode": "en"}, {"longText": "Australia", "shortText": "AU", "types": ["country", "political"], "languageCode": "en"}, {"longText": "3070", "shortText": "3070", "types": ["postal_code"], "languageCode": "en-AU"}], "location": {"latitude": -37.771772, "longitude": 144.998098}, "businessStatus": "OPERATIONAL", "displayName": {"text": "Doctors of Northcote - Dr. Catherine Maclean", "languageCode": "en"}, "primaryTypeDisplayName": {"text": "Doctor", "languageCode": "en-AU"}, "primaryType": "doctor", "shortFormattedAddress": "295 High St, Northcote"}, {"id": "ChIJaXwTQXxD1moRrvw6FaoZ-b4", "types": ["doctor", "health", "point_of_interest", "establishment"], "formattedAddress": "297 High St, Northcote VIC 3070, Australia", "addressComponents": [{"longText": "297", "shortText": "297", "types": ["street_number"], "languageCode": "en-AU"}, {"longText": "High Street", "shortText": "High St", "types": ["route"], "languageCode": "en"}, {"longText": "Northcote", "shortText": "Northcote", "types": ["locality", "political"], "languageCode": "en"}, {"longText": "Darebin City", "shortText": "Darebin", "types": ["administrative_area_level_2", "political"], "languageCode": "en"}, {"longText": "Victoria", "shortText": "VIC", "types": ["administrative_area_level_1", "political"], "languageCode": "en"}, {"longText": "Australia", "shortText": "AU", "types": ["country", "political"], "languageCode": "en"}, {"longText": "3070", "shortText": "3070", "types": ["postal_code"], "languageCode": "en-AU"}], "location": {"latitude": -37.771708, "longitude": 144.998325}, "businessStatus": "OPERATIONAL", "displayName": {"text": "Lin George", "languageCode": "en"}, "primaryTypeDisplayName": {"text": "Doctor", "languageCode": "en-AU"}, "primaryType": "doctor", "shortFormattedAddress": "297 High St, Northcote"}, {"id": "ChIJNYZcP3xD1moRoC5sGhVSY4E", "types": ["doctor", "health", "point_of_interest", "establishment"], "formattedAddress": "295 High St, Northcote VIC 3070, Australia", "addressComponents": [{"longText": "295", "shortText": "295", "types": ["street_number"], "languageCode": "en-AU"}, {"longText": "High Street", "shortText": "High St", "types": ["route"], "languageCode": "en"}, {"longText": "Northcote", "shortText": "Northcote", "types": ["locality", "political"], "languageCode": "en"}, {"longText": "Darebin City", "shortText": "Darebin", "types": ["administrative_area_level_2", "political"], "languageCode": "en"}, {"longText": "Victoria", "shortText": "VIC", "types": ["administrative_area_level_1", "political"], "languageCode": "en"}, {"longText": "Australia", "shortText": "AU", "types": ["country", "political"], "languageCode": "en"}, {"longText": "3070", "shortText": "3070", "types": ["postal_code"], "languageCode": "en-AU"}], "location": {"latitude": -37.771772, "longitude": 144.998098}, "businessStatus": "OPERATIONAL", "displayName": {"text": "Doctors of Northcote - Dr. Sally Stokes", "languageCode": "en"}, "primaryTypeDisplayName": {"text": "Doctor", "languageCode": "en-AU"}, "primaryType": "doctor", "shortFormattedAddress": "295 High St, Northcote"}, {"id": "ChIJ_0KYQXxD1moRsRjULrn0J3Y", "types": ["doctor", "health", "point_of_interest", "establishment"], "formattedAddress": "295 High St, Northcote VIC 3070, Australia", "addressComponents": [{"longText": "295", "shortText": "295", "types": ["street_number"], "languageCode": "en-AU"}, {"longText": "High Street", "shortText": "High St", "types": ["route"], "languageCode": "en"}, {"longText": "Northcote", "shortText": "Northcote", "types": ["locality", "political"], "languageCode": "en"}, {"longText": "Darebin City", "shortText": "Darebin", "types": ["administrative_area_level_2", "political"], "languageCode": "en"}, {"longText": "Victoria", "shortText": "VIC", "types": ["administrative_area_level_1", "political"], "languageCode": "en"}, {"longText": "Australia", "shortText": "AU", "types": ["country", "political"], "languageCode": "en"}, {"longText": "3070", "shortText": "3070", "types": ["postal_code"], "languageCode": "en-AU"}], "location": {"latitude": -37.771772, "longitude": 144.998098}, "businessStatus": "OPERATIONAL", "displayName": {"text": "DR. James LYNCH", "languageCode": "en"}, "primaryTypeDisplayName": {"text": "Doctor", "languageCode": "en-AU"}, "primaryType": "doctor", "shortFormattedAddress": "295 High St, Northcote"}, {"id": "ChIJdZbUlJpD1moRm9KcFjSbcAk", "types": ["medical_clinic", "doctor", "service", "health", "point_of_interest", "establishment"], "formattedAddress": "273 High St, Northcote VIC 3071, Australia", "addressComponents": [{"longText": "273", "shortText": "273", "types": ["street_number"], "languageCode": "en-AU"}, {"longText": "High Street", "shortText": "High St", "types": ["route"], "languageCode": "en"}, {"longText": "Northcote", "shortText": "Northcote", "types": ["locality", "political"], "languageCode": "en"}, {"longText": "Darebin City", "shortText": "Darebin", "types": ["administrative_area_level_2", "political"], "languageCode": "en"}, {"longText": "Victoria", "shortText": "VIC", "types": ["administrative_area_level_1", "political"], "languageCode": "en"}, {"longText": "Australia", "shortText": "AU", "types": ["country", "political"], "languageCode": "en"}, {"longText": "3071", "shortText": "3071", "types": ["postal_code"], "languageCode": "en-AU"}], "location": {"latitude": -37.7723545, "longitude": 144.9981478}, "businessStatus": "OPERATIONAL", "displayName": {"text": "The Hart Centre", "languageCode": "en"}, "primaryTypeDisplayName": {"text": "Health", "languageCode": "en-AU"}, "primaryType": "health", "shortFormattedAddress": "273 High St, Northcote"}]